CHANGES.rst
CONTRIBUTORS.rst
MANIFEST.in
README.rst
setup.py
src/buildout_helpers/__init__.py
src/buildout_helpers/cmd.py
src/buildout_helpers/freeze.py
src/buildout_helpers/normalize.py
src/buildout_helpers/testing.py
src/buildout_helpers/version_info.py
src/buildout_helpers.egg-info/PKG-INFO
src/buildout_helpers.egg-info/SOURCES.txt
src/buildout_helpers.egg-info/dependency_links.txt
src/buildout_helpers.egg-info/entry_points.txt
src/buildout_helpers.egg-info/not-zip-safe
src/buildout_helpers.egg-info/requires.txt
src/buildout_helpers.egg-info/top_level.txt
src/buildout_helpers/tests/__init__.py
src/buildout_helpers/tests/test_freeze.py
src/buildout_helpers/tests/test_normalize.py
src/buildout_helpers/tests/test_version_info.py