Metadata-Version: 1.1
Name: buildout-helpers
Version: 1.0.1
Summary: A buildout config file normalizer
Home-page: http://pypi.python.org/pypi/buildout_helpers
Author: Patrick Gerken
Author-email: patrick.gerken@zumtobelgroup.com
License: BSD
Keywords: Python Plone
Platform: UNKNOWN
Classifier: Programming Language :: Python
Classifier: Operating System :: OS Independent
Classifier: Programming Language :: Python :: 2.7
Classifier: Programming Language :: Python :: 3.4
Classifier: License :: OSI Approved :: BSD License
